elasticsearch/__init__.py
elasticsearch/compat.py
elasticsearch/connection_pool.py
elasticsearch/exceptions.py
elasticsearch/serializer.py
elasticsearch/transport.py
elasticsearch/client/__init__.py
elasticsearch/client/cat.py
elasticsearch/client/cluster.py
elasticsearch/client/indices.py
elasticsearch/client/ingest.py
elasticsearch/client/nodes.py
elasticsearch/client/remote.py
elasticsearch/client/snapshot.py
elasticsearch/client/tasks.py
elasticsearch/client/utils.py
elasticsearch/client/xpack/__init__.py
elasticsearch/client/xpack/deprecation.py
elasticsearch/client/xpack/graph.py
elasticsearch/client/xpack/license.py
elasticsearch/client/xpack/migration.py
elasticsearch/client/xpack/ml.py
elasticsearch/client/xpack/monitoring.py
elasticsearch/client/xpack/security.py
elasticsearch/client/xpack/watcher.py
elasticsearch/connection/__init__.py
elasticsearch/connection/base.py
elasticsearch/connection/http_requests.py
elasticsearch/connection/http_urllib3.py
elasticsearch/connection/pooling.py
elasticsearch/helpers/__init__.py
elasticsearch/helpers/test.py
elasticsearch5/__init__.py
elasticsearch5/compat.py
elasticsearch5/connection_pool.py
elasticsearch5/exceptions.py
elasticsearch5/serializer.py
elasticsearch5/transport.py
elasticsearch5/client/__init__.py
elasticsearch5/client/cat.py
elasticsearch5/client/cluster.py
elasticsearch5/client/indices.py
elasticsearch5/client/ingest.py
elasticsearch5/client/nodes.py
elasticsearch5/client/remote.py
elasticsearch5/client/snapshot.py
elasticsearch5/client/tasks.py
elasticsearch5/client/utils.py
elasticsearch5/connection/__init__.py
elasticsearch5/connection/base.py
elasticsearch5/connection/http_requests.py
elasticsearch5/connection/http_urllib3.py
elasticsearch5/connection/pooling.py
elasticsearch5/helpers/__init__.py
elasticsearch5/helpers/test.py
elasticsearch5-5.5.5.dist-info/METADATA
elasticsearch5-5.5.5.dist-info/RECORD
elasticsearch5-5.5.5.dist-info/WHEEL
elasticsearch5-5.5.5.dist-info/top_level.txt
