Metadata-Version: 2.1
Name: elasticsearch5
Version: 5.5.5
Summary: Python client for Elasticsearch
Home-page: https://github.com/elastic/elasticsearch-py
Author: Honza Král, Nick Lang
Author-email: honza.kral@gmail.com, nick@nicklang.com
License: Apache License, Version 2.0
Platform: UNKNOWN
Classifier: Development Status :: 5 - Production/Stable
Classifier: License :: OSI Approved :: Apache Software License
Classifier: Intended Audience :: Developers
Classifier: Operating System :: OS Independent
Classifier: Programming Language :: Python
Classifier: Programming Language :: Python :: 2
Classifier: Programming Language :: Python :: 2.6
Classifier: Programming Language :: Python :: 2.7
Classifier: Programming Language :: Python :: 3
Classifier: Programming Language :: Python :: 3.2
Classifier: Programming Language :: Python :: 3.3
Classifier: Programming Language :: Python :: 3.4
Classifier: Programming Language :: Python :: 3.5
Classifier: Programming Language :: Python :: 3.6
Classifier: Programming Language :: Python :: Implementation :: CPython
Classifier: Programming Language :: Python :: Implementation :: PyPy
Provides-Extra: develop
Requires-Dist: urllib3 (>=1.21.1)
Provides-Extra: develop
Requires-Dist: requests (<3.0.0,>=2.0.0); extra == 'develop'
Requires-Dist: nose; extra == 'develop'
Requires-Dist: coverage; extra == 'develop'
Requires-Dist: mock; extra == 'develop'
Requires-Dist: pyaml; extra == 'develop'
Requires-Dist: nosexcover; extra == 'develop'
Requires-Dist: sphinx; extra == 'develop'
Requires-Dist: sphinx-rtd-theme; extra == 'develop'
